LICENSE
README.md
lyyapp.py
setup.py
lyyapp.egg-info/PKG-INFO
lyyapp.egg-info/SOURCES.txt
lyyapp.egg-info/dependency_links.txt
lyyapp.egg-info/top_level.txt