Metadata-Version: 2.1
Name: lyyapp
Version: 1.3
Summary: userfull application for  lyy
Author: lyy
Author-email: 
License: MIT
License-File: LICENSE
